dwoht/__init__.py
dwoht/funcs.py
dwoht/log.py
dwoht/notification.py
dwoht/read_data.py
dwoht/reformat_data.py
dwoht-1.2.1.dist-info/LICENSE
dwoht-1.2.1.dist-info/METADATA
dwoht-1.2.1.dist-info/WHEEL
dwoht-1.2.1.dist-info/top_level.txt
dwoht-1.2.1.dist-info/RECORD
