Metadata-Version: 2.1
Name: dwoht
Version: 1.2.1
Summary: a personal used codebase for some common data processing tasks.
Author-email: ryleesnow <author@example.com>
Classifier: Programming Language :: Python :: 3
Classifier: License :: OSI Approved :: MIT License
Classifier: Operating System :: OS Independent
Requires-Python: >=3.8.13
License-File: LICENSE
Requires-Dist: setuptools >=68
Requires-Dist: pathos >=0.3.0
Requires-Dist: pandas >=1.3.4
Requires-Dist: numpy >=1.22.3
Requires-Dist: pyarrow >=14.0.1
Requires-Dist: tqdm >=4.64.0
